tagrefsorter/__init__.py
tagrefsorter/_version.py
tagrefsorter/cli.py
tagrefsorter-0.1.7.dist-info/METADATA
tagrefsorter-0.1.7.dist-info/WHEEL
tagrefsorter-0.1.7.dist-info/entry_points.txt
tagrefsorter-0.1.7.dist-info/top_level.txt
tagrefsorter-0.1.7.dist-info/RECORD
