Metadata-Version: 2.4
Name: tagrefsorter
Version: 0.1.7
Summary: CLI tool to normalize LaTeX \tag numbering in Jupyter Notebook files
Author-email: SuzuSys <sigmatics@outlook.jp>
License: MIT
Requires-Python: >=3.9
Requires-Dist: nbformat>=5.0
